{
  "updated_at_gst": "2026-03-30 12:06",
  "status": {
    "dxb_dwc": "Suspended until further notice (verify on official advisory)",
    "uae_posture": "High-alert diplomatic/security posture",
    "note": "Use official airport + airline channels before movement."
  },
  "sources": {
    "gdelt_api": "https://api.gdeltproject.org/api/v2/doc/doc",
    "aljazeera_rss": "https://www.aljazeera.com/xml/rss/all.xml",
    "monitor_the_situation": "https://monitor-the-situation.com/middle-east",
    "dubaiairports": "https://www.dubaiairports.ae/",
    "mofa": "https://www.mofa.gov.ae/en"
  },
  "live_api_events": [],
  "headlines": {
    "aljazeera": [
      {
        "title": "US-Israel war on Iran: What’s happening on day 31 of attacks",
        "published": "Mon, 30 Mar 2026 07:15:46 +0000",
        "link": "https://www.aljazeera.com/sports/2026/3/30/mohamed-salah-warned-against-us-move-as-mls-clubs-eye-egyptian-footballer?traffic_source=rss"
      },
      {
        "title": "Iranian academic describes US-Israeli attacks on Iran’s universities",
        "published": "Mon, 30 Mar 2026 01:24:55 +0000",
        "link": "https://www.aljazeera.com/video/newsfeed/2026/3/30/netanyahu-orders-deeper-israeli-invasion-into-lebanon?traffic_source=rss"
      },
      {
        "title": "Oil tops $116 a barrel as Iran accuses US of preparing invasion",
        "published": "Mon, 30 Mar 2026 00:53:36 +0000",
        "link": "https://www.aljazeera.com/news/2026/3/30/iranian-attack-damages-kuwait-power-and-desalination-plant-kills-worker?traffic_source=rss"
      },
      {
        "title": "Iran war live: Trump says wants to take Iran’s oil; Kuwait power site hit",
        "published": "Mon, 30 Mar 2026 00:00:44 +0000",
        "link": "https://www.aljazeera.com/video/inside-story/2026/3/29/how-will-the-houthis-involvement-shape-the-war?traffic_source=rss"
      }
    ],
    "monitor_the_situation": []
  }
}