{
  "updated_at_gst": "2026-04-14 16:55",
  "status": {
    "dxb_dwc": "Suspended until further notice (verify on official advisory)",
    "uae_posture": "High-alert diplomatic/security posture",
    "note": "Use official airport + airline channels before movement."
  },
  "sources": {
    "gdelt_api": "https://api.gdeltproject.org/api/v2/doc/doc",
    "aljazeera_rss": "https://www.aljazeera.com/xml/rss/all.xml",
    "monitor_the_situation": "https://monitor-the-situation.com/middle-east",
    "dubaiairports": "https://www.dubaiairports.ae/",
    "mofa": "https://www.mofa.gov.ae/en"
  },
  "live_api_events": [],
  "headlines": {
    "aljazeera": [
      {
        "title": "How much will US Hormuz blockade hurt Iran, and does Tehran have an escape?",
        "published": "Tue, 14 Apr 2026 12:31:34 +0000",
        "link": "https://www.aljazeera.com/news/2026/4/14/how-many-ships-have-passed-the-strait-of-hormuz-and-how-many-were-attacked?traffic_source=rss"
      },
      {
        "title": "What we know about US-hosted talks between Israel and Lebanon",
        "published": "Tue, 14 Apr 2026 10:37:30 +0000",
        "link": "https://www.aljazeera.com/news/2026/4/14/israel-lebanon-direct-talks-in-the-us-all-to-know?traffic_source=rss"
      },
      {
        "title": "Iran slams YouTube ban on pro-Iranian group’s Lego-style AI videos",
        "published": "Tue, 14 Apr 2026 10:16:25 +0000",
        "link": "https://www.aljazeera.com/news/2026/4/14/sanctioned-tankers-transit-strait-of-hormuz-despite-blockade?traffic_source=rss"
      },
      {
        "title": "Iran war: What is happening on day 46 of the US-Iran conflict?",
        "published": "Tue, 14 Apr 2026 06:58:20 +0000",
        "link": "https://www.aljazeera.com/news/2026/4/14/china-dismisses-vice-minister-of-foreign-affairs-sun-weidong?traffic_source=rss"
      }
    ],
    "monitor_the_situation": [
      {
        "title": "— Real-time AIS positions of naval vessels, carrier strike groups, and commercial shipping",
        "published": "line-1",
        "link": "https://monitor-the-situation.com/middle-east"
      },
      {
        "title": "— Israel, Iran, Syria, Yemen, Gulf",
        "published": "line-2",
        "link": "https://monitor-the-situation.com/middle-east"
      }
    ]
  }
}