{
  "updated_at_gst": "2026-04-24 19:44",
  "status": {
    "dxb_dwc": "Suspended until further notice (verify on official advisory)",
    "uae_posture": "High-alert diplomatic/security posture",
    "note": "Use official airport + airline channels before movement."
  },
  "sources": {
    "gdelt_api": "https://api.gdeltproject.org/api/v2/doc/doc",
    "aljazeera_rss": "https://www.aljazeera.com/xml/rss/all.xml",
    "monitor_the_situation": "https://monitor-the-situation.com/middle-east",
    "dubaiairports": "https://www.dubaiairports.ae/",
    "mofa": "https://www.mofa.gov.ae/en"
  },
  "live_api_events": [],
  "headlines": {
    "aljazeera": [
      {
        "title": "Iran-Iraq Tanker War redux? Why the Strait of Hormuz crisis is different",
        "published": "Fri, 24 Apr 2026 15:00:21 +0000",
        "link": "https://www.aljazeera.com/news/2026/4/24/israels-benjamin-netanyahu-says-he-received-treatment-for-prostate-cancer?traffic_source=rss"
      },
      {
        "title": "UK to end project tracking potential Israeli violations: Report",
        "published": "Fri, 24 Apr 2026 14:37:04 +0000",
        "link": "https://www.aljazeera.com/video/newsfeed/2026/4/24/us-navy-authorised-to-target-iranian-fast-boats-in-strait-of-hormuz?traffic_source=rss"
      },
      {
        "title": "Iranian FM Araghchi to visit Pakistan in step towards US talks resumption",
        "published": "Fri, 24 Apr 2026 12:57:22 +0000",
        "link": "https://www.aljazeera.com/video/newsfeed/2026/4/24/whats-been-happening-during-the-lebanon-ceasefire?traffic_source=rss"
      },
      {
        "title": "How long can Iran survive the US’s Hormuz blockade?",
        "published": "Fri, 24 Apr 2026 11:26:11 +0000",
        "link": "https://www.aljazeera.com/news/2026/4/24/number-of-amputees-set-to-rise-in-gaza-as-israel-blocks-aid-ngo-warns?traffic_source=rss"
      }
    ],
    "monitor_the_situation": [
      {
        "title": "— Real-time AIS positions of naval vessels, carrier strike groups, and commercial shipping",
        "published": "line-1",
        "link": "https://monitor-the-situation.com/middle-east"
      },
      {
        "title": "— Israel, Iran, Syria, Yemen, Gulf",
        "published": "line-2",
        "link": "https://monitor-the-situation.com/middle-east"
      }
    ]
  }
}