{
  "updated_at_gst": "2026-04-25 04:04",
  "status": {
    "dxb_dwc": "Suspended until further notice (verify on official advisory)",
    "uae_posture": "High-alert diplomatic/security posture",
    "note": "Use official airport + airline channels before movement."
  },
  "sources": {
    "gdelt_api": "https://api.gdeltproject.org/api/v2/doc/doc",
    "aljazeera_rss": "https://www.aljazeera.com/xml/rss/all.xml",
    "monitor_the_situation": "https://monitor-the-situation.com/middle-east",
    "dubaiairports": "https://www.dubaiairports.ae/",
    "mofa": "https://www.mofa.gov.ae/en"
  },
  "live_api_events": [],
  "headlines": {
    "aljazeera": [
      {
        "title": "Israel continues attacks on Lebanon despite extension of ceasefire",
        "published": "Fri, 24 Apr 2026 20:46:38 +0000",
        "link": "https://www.aljazeera.com/news/2026/4/24/trump-to-again-end-legal-status-of-people-who-entered-us-with-cbp-one-app?traffic_source=rss"
      },
      {
        "title": "Can Europe help the Middle East resolve the war on Iran?",
        "published": "Fri, 24 Apr 2026 19:05:10 +0000",
        "link": "https://www.aljazeera.com/economy/2026/4/24/trump-government-extends-jones-act-waiver-by-90-days-to-dampen-oil-prices?traffic_source=rss"
      },
      {
        "title": "Reality check: Israeli ambitions confront US dictates in Iran and Lebanon",
        "published": "Fri, 24 Apr 2026 18:21:33 +0000",
        "link": "https://www.aljazeera.com/news/2026/4/24/kosovo-court-jails-three-serb-separatists-over-2023-banjska-attack?traffic_source=rss"
      },
      {
        "title": "How Israel targeted and killed Lebanese journalist Amal Khalil",
        "published": "Fri, 24 Apr 2026 17:14:03 +0000",
        "link": "https://www.aljazeera.com/features/2026/4/24/russian-oil-exports-slump-as-ukraine-hammers-ports-and-refineries?traffic_source=rss"
      }
    ],
    "monitor_the_situation": [
      {
        "title": "— Real-time AIS positions of naval vessels, carrier strike groups, and commercial shipping",
        "published": "line-1",
        "link": "https://monitor-the-situation.com/middle-east"
      },
      {
        "title": "— Israel, Iran, Syria, Yemen, Gulf",
        "published": "line-2",
        "link": "https://monitor-the-situation.com/middle-east"
      }
    ]
  }
}