{
  "updated_at_gst": "2026-03-24 14:39",
  "status": {
    "dxb_dwc": "Suspended until further notice (verify on official advisory)",
    "uae_posture": "High-alert diplomatic/security posture",
    "note": "Use official airport + airline channels before movement."
  },
  "sources": {
    "gdelt_api": "https://api.gdeltproject.org/api/v2/doc/doc",
    "aljazeera_rss": "https://www.aljazeera.com/xml/rss/all.xml",
    "monitor_the_situation": "https://monitor-the-situation.com/middle-east",
    "dubaiairports": "https://www.dubaiairports.ae/",
    "mofa": "https://www.mofa.gov.ae/en"
  },
  "live_api_events": [],
  "headlines": {
    "aljazeera": [
      {
        "title": "Iran launches waves of missiles towards Israel",
        "published": "Tue, 24 Mar 2026 10:05:05 +0000",
        "link": "https://www.aljazeera.com/video/newsfeed/2026/3/24/iran-says-no-talks-with-us-calls-trump-statements-a?traffic_source=rss"
      },
      {
        "title": "Drone footage shows aftermath of Iranian missile attack in Tel Aviv",
        "published": "Tue, 24 Mar 2026 09:29:59 +0000",
        "link": "https://www.aljazeera.com/sports/2026/3/24/mccullum-to-continue-as-englands-all-format-cricket-head-coach?traffic_source=rss"
      },
      {
        "title": "Deadly air attack hits pro-Iran Popular Mobilisation Forces in Iraq",
        "published": "Tue, 24 Mar 2026 08:43:47 +0000",
        "link": "https://www.aljazeera.com/video/newsfeed/2026/3/24/al-jazeera-reports-from-scene-of-attack-on-tehran-residential-area?traffic_source=rss"
      },
      {
        "title": "Despite Trump’s peace talk claims, US-Israeli attacks continue to hit Iran",
        "published": "Tue, 24 Mar 2026 08:14:59 +0000",
        "link": "https://www.aljazeera.com/video/newsfeed/2026/3/24/top-eu-official-calls-for-negotiations-with-iran-and-an-end-to-war?traffic_source=rss"
      },
      {
        "title": "Palestine weekly wrap: West Bank attacks surge, Israel restricts Gaza aid",
        "published": "Tue, 24 Mar 2026 06:25:55 +0000",
        "link": "https://www.aljazeera.com/sports/2026/3/24/mbappe-fit-and-ready-to-play-every-real-madrid-game-before-world-cup?traffic_source=rss"
      },
      {
        "title": "US-Israel war on Iran: What’s happening on day 25 of attacks?",
        "published": "Tue, 24 Mar 2026 06:17:43 +0000",
        "link": "https://www.aljazeera.com/sports/2026/3/24/tiger-woods-eyes-masters-return-with-competitive-golf-outing-at-tgl?traffic_source=rss"
      }
    ],
    "monitor_the_situation": []
  }
}