{
  "updated_at_gst": "2026-06-09 22:25",
  "status": {
    "dxb_dwc": "Suspended until further notice (verify on official advisory)",
    "uae_posture": "High-alert diplomatic/security posture",
    "note": "Use official airport + airline channels before movement."
  },
  "sources": {
    "gdelt_api": "https://api.gdeltproject.org/api/v2/doc/doc",
    "aljazeera_rss": "https://www.aljazeera.com/xml/rss/all.xml",
    "monitor_the_situation": "https://monitor-the-situation.com/middle-east",
    "dubaiairports": "https://www.dubaiairports.ae/",
    "mofa": "https://www.mofa.gov.ae/en"
  },
  "live_api_events": [],
  "headlines": {
    "aljazeera": [
      {
        "title": "Israel preventing more than 16,500 Palestinians from accessing medical treatment",
        "published": "Tue, 09 Jun 2026 18:08:52 +0000",
        "link": "https://www.aljazeera.com/news/2026/6/9/anything-but-normal-uncertainty-as-iranians-try-to-get-by-amid-us-war?traffic_source=rss"
      },
      {
        "title": "Palestinians confront Israeli settlers over land grab near Hebron",
        "published": "Tue, 09 Jun 2026 17:55:51 +0000",
        "link": "https://www.aljazeera.com/video/newsfeed/2026/6/9/mexico-prepares-for-world-cup-opening-match-amid-protests?traffic_source=rss"
      },
      {
        "title": "Trump says in ‘final throes’ of peace deal but at least 8 killed in Lebanon",
        "published": "Tue, 09 Jun 2026 13:41:52 +0000",
        "link": "https://www.aljazeera.com/features/2026/6/9/shackled-bleeding-raped-palestinians-describe-abuse-in-israels-prisons?traffic_source=rss"
      }
    ],
    "monitor_the_situation": [
      {
        "title": "— Real-time AIS positions of naval vessels, carrier strike groups, and commercial shipping",
        "published": "line-1",
        "link": "https://monitor-the-situation.com/middle-east"
      },
      {
        "title": "— Israel, Iran, Syria, Yemen, Gulf",
        "published": "line-2",
        "link": "https://monitor-the-situation.com/middle-east"
      }
    ]
  }
}