{
  "updated_at_gst": "2026-03-31 22:43",
  "status": {
    "dxb_dwc": "Suspended until further notice (verify on official advisory)",
    "uae_posture": "High-alert diplomatic/security posture",
    "note": "Use official airport + airline channels before movement."
  },
  "sources": {
    "gdelt_api": "https://api.gdeltproject.org/api/v2/doc/doc",
    "aljazeera_rss": "https://www.aljazeera.com/xml/rss/all.xml",
    "monitor_the_situation": "https://monitor-the-situation.com/middle-east",
    "dubaiairports": "https://www.dubaiairports.ae/",
    "mofa": "https://www.mofa.gov.ae/en"
  },
  "live_api_events": [],
  "headlines": {
    "aljazeera": [
      {
        "title": "Palestinians in occupied West Bank protest Israel’s death penalty law",
        "published": "Tue, 31 Mar 2026 18:18:12 +0000",
        "link": "https://www.aljazeera.com/video/newsfeed/2026/3/31/israeli-strike-hits-building-in-beiruts-southern-suburbs?traffic_source=rss"
      },
      {
        "title": "US-Israel launch major attacks as Iranian authorities maintain defiance",
        "published": "Tue, 31 Mar 2026 18:07:51 +0000",
        "link": "https://www.aljazeera.com/news/2026/3/31/one-month-of-war-in-middle-east-cost-arab-states-up-to-194bn-undp?traffic_source=rss"
      },
      {
        "title": "Why Iran believes it can outlast the US",
        "published": "Tue, 31 Mar 2026 17:04:51 +0000",
        "link": "https://www.aljazeera.com/video/newsfeed/2026/3/31/qatar-says-ready-to-help-with-us-iran-negotiations?traffic_source=rss"
      },
      {
        "title": "Trump attacks NATO allies as pressure mounts over Strait of Hormuz",
        "published": "Tue, 31 Mar 2026 16:01:59 +0000",
        "link": "https://www.aljazeera.com/news/2026/3/31/qatar-warns-iranian-attacks-on-region-causing-catastrophic-effects?traffic_source=rss"
      },
      {
        "title": "Venezuela’s ‘Chavismo’ movement faces a crossroads after US attack",
        "published": "Tue, 31 Mar 2026 15:11:33 +0000",
        "link": "https://www.aljazeera.com/opinions/2026/3/31/the-attack-on-the-right-to-protest-in-the-uk-is-not-just-about-palestine?traffic_source=rss"
      },
      {
        "title": "Iran will play World Cup games in US despite war, FIFA’s Infantino says",
        "published": "Tue, 31 Mar 2026 14:43:57 +0000",
        "link": "https://www.aljazeera.com/news/2026/3/31/where-to-invest-during-iran-war-ask-or-dont-mohammad-bagher-ghalibaf?traffic_source=rss"
      }
    ],
    "monitor_the_situation": []
  }
}